[
    
	
	
	
    {
        "name": "Iron Ore Enrichment Zone",
        "resourceType": "Strategic",
        "revealedBy": "Ore Prospecting",
        "improvedBy": ["Iron Ore Mine","Unmanned Mining Station"],
        "terrainsCanBeFoundOn": ["Void","Interstellar Dust","Asteroid Belt"],
        "uniques": [
            "Generated on every [80] tiles <in [{Featureless} {Void}] tiles>",
            "Generated on every [40] tiles <in [Interstellar Dust] tiles>",
            "Generated on every [40] tiles <in [Asteroid Belt] tiles>",
            "Cannot be traded",
            "Not shown on world screen"
        ]
    },
    {
        "name": "Rare Metal Enrichment Zone",
        "resourceType": "Strategic",
        "revealedBy": "Ore Prospecting",
        "improvedBy": ["Rare Metal Mine","Unmanned Mining Station"],
        "terrainsCanBeFoundOn": ["Void","Interstellar Dust","Asteroid Belt"],
        "uniques": [
            "Generated on every [90] tiles <in [{Featureless} {Void}] tiles>",
            "Generated on every [50] tiles <in [Interstellar Dust] tiles>",
            "Generated on every [50] tiles <in [Asteroid Belt] tiles>",
            "Cannot be traded",
            "Not shown on world screen"
        ]
    },
    {
        "name": "Helium-3 Enrichment Zone",
        "resourceType": "Strategic",
        "revealedBy": "Nuclear Fusion Device",
        "improvedBy": ["Helium-3 Mine"],
        "terrainsCanBeFoundOn": ["Void","Interstellar Dust","Asteroid Belt"],
        "uniques": [
            "Generated on every [100] tiles <in [{Featureless} {Void}] tiles>",
            "Generated on every [70] tiles <in [Interstellar Dust] tiles>",
            "Generated on every [50] tiles <in [Asteroid Belt] tiles>",
            "Cannot be traded",
            "Not shown on world screen"
        ]
    },
    {
        "name": "Focus Ore Enrichment Zone",
        "resourceType": "Strategic",
        "revealedBy": "Mining Equipment Optimization",
        "improvedBy": ["Focus Ore Mine","Unmanned Mining Station"],
        "terrainsCanBeFoundOn": ["Void","Interstellar Dust","Asteroid Belt"],
        "uniques": [
            "Generated on every [100] tiles <in [{Featureless} {Void}] tiles>",
            "Generated on every [45] tiles <in [Interstellar Dust] tiles>",
            "Generated on every [60] tiles <in [Asteroid Belt] tiles>",
            "Cannot be traded",
            "Not shown on world screen"
        ]
    },
    {
        "name": "Space Biological Settlement",
        "resourceType": "Strategic",
        "revealedBy": "Space Species Research",
        "improvedBy": ["Space Biological Farm"],
        "terrainsCanBeFoundOn": ["Void","Interstellar Dust","Asteroid Belt"],
        "uniques": [
            "Generated on every [60] tiles <in [{Featureless} {Void}] tiles>",
            "Generated on every [90] tiles <in [Interstellar Dust] tiles>",
            "Generated on every [140] tiles <in [Asteroid Belt] tiles>",
            "Cannot be traded",
            "Not shown on world screen"
        ]
    },
    
    
    
    
    
    
    {
        "name": "Dark Matter",
        "resourceType": "Strategic",
        "revealedBy": "Cosmology",
        "improvedBy": ["Dark Matter Extractor"],
        "terrainsCanBeFoundOn": ["Void","Interstellar Dust","Asteroid Belt"],
        "uniques": [
            "Cannot be traded",
            "Stockpiled",
            //"Not shown on world screen"
            "Generated on every [300] tiles <in [Void] tiles>",
            
            
            
            
        ]
    },
    
    
    
    
    
    
    
    {
        "name": "Iron Ore",
        "resourceType": "Strategic",
        "uniques": [
            "Cannot be traded",
            "Stockpiled",
            //"Not shown on world screen"
        ]
    },
    {
        "name": "Rare Metal Ore",
        "resourceType": "Strategic",
        "uniques": [
            "Cannot be traded",
            "Stockpiled",
            //"Not shown on world screen"
        ]
    },
    {
        "name": "Helium-3",
        "resourceType": "Strategic",
        "uniques": [
            "Cannot be traded",
            "Stockpiled",
            //"Not shown on world screen"
        ]
    },
    {
        "name": "Focus Ore",
        "resourceType": "Strategic",
        "uniques": [
            "Cannot be traded",
            "Stockpiled",
            //"Not shown on world screen"
        ]
    },
    {
        "name": "Interstellar Debris",
        "resourceType": "Strategic",
        "uniques": [
            "Cannot be traded",
            "Stockpiled",
            //"Not shown on world screen"
        ]
    },
    
    
    
    
    
    
    
    
    
    {
        "name": "Alloy",
        "resourceType": "Strategic",
        "uniques": [
            "Cannot be traded",
            "Stockpiled",
            //"Not shown on world screen"
        ]
    },
    {
        "name": "Rare Metal",
        "resourceType": "Strategic",
        "uniques": [
            "Cannot be traded",
            "Stockpiled",
            //"Not shown on world screen"
        ]
    },
    {
        "name": "Focus Crystal",
        "resourceType": "Strategic",
        "uniques": [
            "Cannot be traded",
            "Stockpiled",
            //"Not shown on world screen"
        ]
    },
    
    
    
    
    {
        "name": "Light Alloy",
        "resourceType": "Strategic",
        "uniques": [
            "Cannot be traded",
            "Stockpiled",
            //"Not shown on world screen"
        ]
    },
    {
        "name": "Tough Alloy",
        "resourceType": "Strategic",
        "uniques": [
            "Cannot be traded",
            "Stockpiled",
            //"Not shown on world screen"
        ]
    },
    
    
    
    
    
    
    
    
    {
        "name": "Industrial Capacity",
        "resourceType": "Strategic",
        "uniques": [
            "Cannot be traded",
            //"Stockpiled",
            //"Not shown on world screen"
        ]
    },
    {
        "name": "[Iron Ore] Processing Capacity",
        "resourceType": "Strategic",
        "uniques": [
            "Cannot be traded",
            "Stockpiled",
            "Not shown on world screen"
        ]
    },
    {
        "name": "[Rare Metal Ore] Processing Capacity",
        "resourceType": "Strategic",
        "uniques": [
            "Cannot be traded",
            "Stockpiled",
            "Not shown on world screen"
        ]
    },
    {
        "name": "[Focus Ore] Processing Capacity",
        "resourceType": "Strategic",
        "uniques": [
            "Cannot be traded",
            "Stockpiled",
            "Not shown on world screen"
        ]
    },
    {
        "name": "[Interstellar Debris] Processing Capacity",
        "resourceType": "Strategic",
        "uniques": [
            "Cannot be traded",
            "Stockpiled",
            "Not shown on world screen"
        ]
    },
    
    
    
    
    {
        "name": "[Light Alloy] Processing Capacity",
        "resourceType": "Strategic",
        "uniques": [
            "Cannot be traded",
            "Stockpiled",
            "Not shown on world screen"
        ]
    },
    {
        "name": "[Tough Alloy] Processing Capacity",
        "resourceType": "Strategic",
        "uniques": [
            "Cannot be traded",
            "Stockpiled",
            "Not shown on world screen"
        ]
    },
    
    
    
    
    
    
    
    {
        "name": "Number of Population",
        "resourceType": "Strategic",
        "uniques": [
            "Cannot be traded",
            "Not shown on world screen"
        ]
    },
    {
        "name": "Manpower",
        "resourceType": "Strategic",
        "uniques": [
            "Cannot be traded",
            "Stockpiled",
            //"Not shown on world screen"
        ]
    },
    {
        "name": "Manpower Max",
        "resourceType": "Strategic",
        "uniques": [
            "Cannot be traded",
            //"Stockpiled",
            //"Not shown on world screen"
        ]
    },
    {
        "name": "Manpower Growth Rate",
        "resourceType": "Strategic",
        "uniques": [
            "Cannot be traded",
            //"Stockpiled",
            //"Not shown on world screen"
        ]
    },
    
	{
        "name": "Space Station Division",
        "resourceType": "Strategic",
        "uniques": [
            "Cannot be traded",
            "City-level resource",
        ]
    },
	{
        "name": "Number of Space Station",
        "resourceType": "Strategic",
        "uniques": [
            "Cannot be traded",
            "Not shown on world screen"
        ]
    },
	
	
	
	{
        "name": "Number of Origin",
        "resourceType": "Strategic",
        "uniques": [
            "Cannot be traded",
            "Not shown on world screen"
        ]
    },
	{
        "name": "Number of Ethos",
        "resourceType": "Strategic",
        "uniques": [
            "Cannot be traded",
            "Not shown on world screen"
        ]
    },
	{
        "name": "Number of Tradition",
        "resourceType": "Strategic",
        "uniques": [
            "Cannot be traded",
            "Not shown on world screen"
        ]
    },
    {
        "name": "Number of Tradition Branch",
        "resourceType": "Strategic",
        "uniques": [
            "Cannot be traded",
            "Not shown on world screen"
        ]
    },
	{
        "name": "Value required for the next tradition",
        "resourceType": "Strategic",
        "uniques": [
            "Cannot be traded",
            "Not shown on world screen"
        ]
    },
	
	{
        "name": "Influence",
        "resourceType": "Strategic",
        "uniques": [
            "Cannot be traded",
            "Stockpiled",
        ]
    },
	{
        "name": "Consumption of Influence",
        "resourceType": "Strategic",
        "uniques": [
            "Cannot be traded",
            "Not shown on world screen"
        ]
    },
	{
        "name": "Empire Scale",
        "resourceType": "Strategic",
        "uniques": [
            "Cannot be traded",
            //"Not shown on world screen"
        ]
    },
    {
        "name": "Empire Scale Penalty",
        "resourceType": "Strategic",
        "uniques": [
            "Cannot be traded",
            "Not shown on world screen"
        ]
    },
	{
        "name": "Population Scale",
        "resourceType": "Strategic",
        "uniques": [
            "Cannot be traded",
            "Not shown on world screen"
        ]
    },
    {
        "name": "Territory Scale",
        "resourceType": "Strategic",
        "uniques": [
            "Cannot be traded",
            "Not shown on world screen"
        ]
    },
    {
        "name": "City Scale",
        "resourceType": "Strategic",
        "uniques": [
            "Cannot be traded",
            "Not shown on world screen"
        ]
    },
    {
        "name": "Population Scale Coefficient",
        "resourceType": "Strategic",
        "uniques": [
            "Cannot be traded",
            "Not shown on world screen"
        ]
    },
    {
        "name": "Territory Scale Coefficient",
        "resourceType": "Strategic",
        "uniques": [
            "Cannot be traded",
            "Not shown on world screen"
        ]
    },
    {
        "name": "City Scale Coefficient",
        "resourceType": "Strategic",
        "uniques": [
            "Cannot be traded",
            "Not shown on world screen"
        ]
    },
    {
        "name": "RN1",
        "resourceType": "Strategic",
        "uniques": [
            "Cannot be traded",
            "Not shown on world screen"
        ]
    },
]






